Workbook

Sheet Dashboard
Q1: Product | R1: Units Sold | T1: Region | U1: Sales | W1: Product | X1: Sales | Z1: Sales Person | AA1: Sales
B2: S | C2: SALES PERFORMANCE DASHBOARD | Q2: Action Figure | R2: =SUMPRODUCT(((('Sales Data'!$C$2:$C$5001=$C$6)+($C$6="All"))>0)*((('Sales Data'!$B$2:$B$5001=$F$6)+($F$6="All"))>0)*((('Sales Data'!$D$2:$D$5001=$I$6)+($I$6="All"))>0)*('Sales Data'!$D$2:$D$5001=Q2)*'Sales Data'!$E$2:$E$5001) | T2: North | U2: =SUMPRODUCT(((('Sales Data'!$C$2:$C$5001=$C$6)+($C$6="All"))>0)*((('Sales Data'!$B$2:$B$5001=$F$6)+($F$6="All"))>0)*((('Sales Data'!$D$2:$D$5001=$I$6)+($I$6="All"))>0)*('Sales Data'!$C$2:$C$5001=T2)*'Sales Data'!$H$2:$H$5001) | W2: Action Figure | X2: =SUMPRODUCT(((('Sales Data'!$C$2:$C$5001=$C$6)+($C$6="All"))>0)*((('Sales Data'!$B$2:$B$5001=$F$6)+($F$6="All"))>0)*((('Sales Data'!$D$2:$D$5001=$I$6)+($I$6="All"))>0)*('Sales Data'!$D$2:$D$5001=W2)*'Sales Data'!$H$2:$H$5001) | Z2: Andrew | AA2: =SUMPRODUCT(((('Sales Data'!$C$2:$C$5001=$C$6)+($C$6="All"))>0)*((('Sales Data'!$B$2:$B$5001=$F$6)+($F$6="All"))>0)*((('Sales Data'!$D$2:$D$5001=$I$6)+($I$6="All"))>0)*('Sales Data'!$B$2:$B$5001=Z2)*'Sales Data'!$H$2:$H$5001)
Q3: Blender | R3: =SUMPRODUCT(((('Sales Data'!$C$2:$C$5001=$C$6)+($C$6="All"))>0)*((('Sales Data'!$B$2:$B$5001=$F$6)+($F$6="All"))>0)*((('Sales Data'!$D$2:$D$5001=$I$6)+($I$6="All"))>0)*('Sales Data'!$D$2:$D$5001=Q3)*'Sales Data'!$E$2:$E$5001) | T3: South | U3: =SUMPRODUCT(((('Sales Data'!$C$2:$C$5001=$C$6)+($C$6="All"))>0)*((('Sales Data'!$B$2:$B$5001=$F$6)+($F$6="All"))>0)*((('Sales Data'!$D$2:$D$5001=$I$6)+($I$6="All"))>0)*('Sales Data'!$C$2:$C$5001=T3)*'Sales Data'!$H$2:$H$5001) | W3: Blender | X3: =SUMPRODUCT(((('Sales Data'!$C$2:$C$5001=$C$6)+($C$6="All"))>0)*((('Sales Data'!$B$2:$B$5001=$F$6)+($F$6="All"))>0)*((('Sales Data'!$D$2:$D$5001=$I$6)+($I$6="All"))>0)*('Sales Data'!$D$2:$D$5001=W3)*'Sales Data'!$H$2:$H$5001) | Z3: Anna | AA3: =SUMPRODUCT(((('Sales Data'!$C$2:$C$5001=$C$6)+($C$6="All"))>0)*((('Sales Data'!$B$2:$B$5001=$F$6)+($F$6="All"))>0)*((('Sales Data'!$D$2:$D$5001=$I$6)+($I$6="All"))>0)*('Sales Data'!$B$2:$B$5001=Z3)*'Sales Data'!$H$2:$H$5001)
B4: Interactive sales analysis | Dataset dates: 2020–2021 | Q4: Moisturizer | R4: =SUMPRODUCT(((('Sales Data'!$C$2:$C$5001=$C$6)+($C$6="All"))>0)*((('Sales Data'!$B$2:$B$5001=$F$6)+($F$6="All"))>0)*((('Sales Data'!$D$2:$D$5001=$I$6)+($I$6="All"))>0)*('Sales Data'!$D$2:$D$5001=Q4)*'Sales Data'!$E$2:$E$5001) | T4: East | U4: =SUMPRODUCT(((('Sales Data'!$C$2:$C$5001=$C$6)+($C$6="All"))>0)*((('Sales Data'!$B$2:$B$5001=$F$6)+($F$6="All"))>0)*((('Sales Data'!$D$2:$D$5001=$I$6)+($I$6="All"))>0)*('Sales Data'!$C$2:$C$5001=T4)*'Sales Data'!$H$2:$H$5001) | W4: Moisturizer | X4: =SUMPRODUCT(((('Sales Data'!$C$2:$C$5001=$C$6)+($C$6="All"))>0)*((('Sales Data'!$B$2:$B$5001=$F$6)+($F$6="All"))>0)*((('Sales Data'!$D$2:$D$5001=$I$6)+($I$6="All"))>0)*('Sales Data'!$D$2:$D$5001=W4)*'Sales Data'!$H$2:$H$5001) | Z4: Cameron | AA4: =SUMPRODUCT(((('Sales Data'!$C$2:$C$5001=$C$6)+($C$6="All"))>0)*((('Sales Data'!$B$2:$B$5001=$F$6)+($F$6="All"))>0)*((('Sales Data'!$D$2:$D$5001=$I$6)+($I$6="All"))>0)*('Sales Data'!$B$2:$B$5001=Z4)*'Sales Data'!$H$2:$H$5001)
Q5: Novel | R5: =SUMPRODUCT(((('Sales Data'!$C$2:$C$5001=$C$6)+($C$6="All"))>0)*((('Sales Data'!$B$2:$B$5001=$F$6)+($F$6="All"))>0)*((('Sales Data'!$D$2:$D$5001=$I$6)+($I$6="All"))>0)*('Sales Data'!$D$2:$D$5001=Q5)*'Sales Data'!$E$2:$E$5001) | T5: West | U5: =SUMPRODUCT(((('Sales Data'!$C$2:$C$5001=$C$6)+($C$6="All"))>0)*((('Sales Data'!$B$2:$B$5001=$F$6)+($F$6="All"))>0)*((('Sales Data'!$D$2:$D$5001=$I$6)+($I$6="All"))>0)*('Sales Data'!$C$2:$C$5001=T5)*'Sales Data'!$H$2:$H$5001) | W5: Novel | X5: =SUMPRODUCT(((('Sales Data'!$C$2:$C$5001=$C$6)+($C$6="All"))>0)*((('Sales Data'!$B$2:$B$5001=$F$6)+($F$6="All"))>0)*((('Sales Data'!$D$2:$D$5001=$I$6)+($I$6="All"))>0)*('Sales Data'!$D$2:$D$5001=W5)*'Sales Data'!$H$2:$H$5001) | Z5: Carolyn | AA5: =SUMPRODUCT(((('Sales Data'!$C$2:$C$5001=$C$6)+($C$6="All"))>0)*((('Sales Data'!$B$2:$B$5001=$F$6)+($F$6="All"))>0)*((('Sales Data'!$D$2:$D$5001=$I$6)+($I$6="All"))>0)*('Sales Data'!$B$2:$B$5001=Z5)*'Sales Data'!$H$2:$H$5001)
B6: REGION | C6: All | E6: SALES PERSON | F6: All | H6: PRODUCT | I6: All | K6: North | L6: South | Q6: Smartphone | R6: =SUMPRODUCT(((('Sales Data'!$C$2:$C$5001=$C$6)+($C$6="All"))>0)*((('Sales Data'!$B$2:$B$5001=$F$6)+($F$6="All"))>0)*((('Sales Data'!$D$2:$D$5001=$I$6)+($I$6="All"))>0)*('Sales Data'!$D$2:$D$5001=Q6)*'Sales Data'!$E$2:$E$5001) | W6: Smartphone | X6: =SUMPRODUCT(((('Sales Data'!$C$2:$C$5001=$C$6)+($C$6="All"))>0)*((('Sales Data'!$B$2:$B$5001=$F$6)+($F$6="All"))>0)*((('Sales Data'!$D$2:$D$5001=$I$6)+($I$6="All"))>0)*('Sales Data'!$D$2:$D$5001=W6)*'Sales Data'!$H$2:$H$5001) | Z6: Connor | AA6: =SUMPRODUCT(((('Sales Data'!$C$2:$C$5001=$C$6)+($C$6="All"))>0)*((('Sales Data'!$B$2:$B$5001=$F$6)+($F$6="All"))>0)*((('Sales Data'!$D$2:$D$5001=$I$6)+($I$6="All"))>0)*('Sales Data'!$B$2:$B$5001=Z6)*'Sales Data'!$H$2:$H$5001)
K7: East | L7: West | Q7: Sneakers | R7: =SUMPRODUCT(((('Sales Data'!$C$2:$C$5001=$C$6)+($C$6="All"))>0)*((('Sales Data'!$B$2:$B$5001=$F$6)+($F$6="All"))>0)*((('Sales Data'!$D$2:$D$5001=$I$6)+($I$6="All"))>0)*('Sales Data'!$D$2:$D$5001=Q7)*'Sales Data'!$E$2:$E$5001) | W7: Sneakers | X7: =SUMPRODUCT(((('Sales Data'!$C$2:$C$5001=$C$6)+($C$6="All"))>0)*((('Sales Data'!$B$2:$B$5001=$F$6)+($F$6="All"))>0)*((('Sales Data'!$D$2:$D$5001=$I$6)+($I$6="All"))>0)*('Sales Data'!$D$2:$D$5001=W7)*'Sales Data'!$H$2:$H$5001) | Z7: Ella | AA7: =SUMPRODUCT(((('Sales Data'!$C$2:$C$5001=$C$6)+($C$6="All"))>0)*((('Sales Data'!$B$2:$B$5001=$F$6)+($F$6="All"))>0)*((('Sales Data'!$D$2:$D$5001=$I$6)+($I$6="All"))>0)*('Sales Data'!$B$2:$B$5001=Z7)*'Sales Data'!$H$2:$H$5001)
B8: TOTAL SALES | E8: AVG. TRANSACTION SALES | H8: UNITS SOLD | K8: PROFIT | Q8: Tent | R8: =SUMPRODUCT(((('Sales Data'!$C$2:$C$5001=$C$6)+($C$6="All"))>0)*((('Sales Data'!$B$2:$B$5001=$F$6)+($F$6="All"))>0)*((('Sales Data'!$D$2:$D$5001=$I$6)+($I$6="All"))>0)*('Sales Data'!$D$2:$D$5001=Q8)*'Sales Data'!$E$2:$E$5001) | W8: Tent | X8: =SUMPRODUCT(((('Sales Data'!$C$2:$C$5001=$C$6)+($C$6="All"))>0)*((('Sales Data'!$B$2:$B$5001=$F$6)+($F$6="All"))>0)*((('Sales Data'!$D$2:$D$5001=$I$6)+($I$6="All"))>0)*('Sales Data'!$D$2:$D$5001=W8)*'Sales Data'!$H$2:$H$5001) | Z8: Grace | AA8: =SUMPRODUCT(((('Sales Data'!$C$2:$C$5001=$C$6)+($C$6="All"))>0)*((('Sales Data'!$B$2:$B$5001=$F$6)+($F$6="All"))>0)*((('Sales Data'!$D$2:$D$5001=$I$6)+($I$6="All"))>0)*('Sales Data'!$B$2:$B$5001=Z8)*'Sales Data'!$H$2:$H$5001)
B9: =SUMPRODUCT(((('Sales Data'!$C$2:$C$5001=$C$6)+($C$6="All"))>0)*((('Sales Data'!$B$2:$B$5001=$F$6)+($F$6="All"))>0)*((('Sales Data'!$D$2:$D$5001=$I$6)+($I$6="All"))>0)*'Sales Data'!$H$2:$H$5001) | E9: =IFERROR(SUMPRODUCT(((('Sales Data'!$C$2:$C$5001=$C$6)+($C$6="All"))>0)*((('Sales Data'!$B$2:$B$5001=$F$6)+($F$6="All"))>0)*((('Sales Data'!$D$2:$D$5001=$I$6)+($I$6="All"))>0)*'Sales Data'!$H$2:$H$5001)/SUMPRODUCT(((('Sales Data'!$C$2:$C$5001=$C$6)+($C$6="All"))>0)*((('Sales Data'!$B$2:$B$5001=$F$6)+($F$6="All"))>0)*((('Sales Data'!$D$2:$D$5001=$I$6)+($I$6="All"))>0)*('Sales Data'!$H$2:$H$5001<>0)),0) | H9: =SUMPRODUCT(((('Sales Data'!$C$2:$C$5001=$C$6)+($C$6="All"))>0)*((('Sales Data'!$B$2:$B$5001=$F$6)+($F$6="All"))>0)*((('Sales Data'!$D$2:$D$5001=$I$6)+($I$6="All"))>0)*'Sales Data'!$E$2:$E$5001) | K9: =SUMPRODUCT(((('Sales Data'!$C$2:$C$5001=$C$6)+($C$6="All"))>0)*((('Sales Data'!$B$2:$B$5001=$F$6)+($F$6="All"))>0)*((('Sales Data'!$D$2:$D$5001=$I$6)+($I$6="All"))>0)*'Sales Data'!$I$2:$I$5001) | Z9: Megan | AA9: =SUMPRODUCT(((('Sales Data'!$C$2:$C$5001=$C$6)+($C$6="All"))>0)*((('Sales Data'!$B$2:$B$5001=$F$6)+($F$6="All"))>0)*((('Sales Data'!$D$2:$D$5001=$I$6)+($I$6="All"))>0)*('Sales Data'!$B$2:$B$5001=Z9)*'Sales Data'!$H$2:$H$5001)
Z10: Nicholas | AA10: =SUMPRODUCT(((('Sales Data'!$C$2:$C$5001=$C$6)+($C$6="All"))>0)*((('Sales Data'!$B$2:$B$5001=$F$6)+($F$6="All"))>0)*((('Sales Data'!$D$2:$D$5001=$I$6)+($I$6="All"))>0)*('Sales Data'!$B$2:$B$5001=Z10)*'Sales Data'!$H$2:$H$5001)
Z11: Virginia | AA11: =SUMPRODUCT(((('Sales Data'!$C$2:$C$5001=$C$6)+($C$6="All"))>0)*((('Sales Data'!$B$2:$B$5001=$F$6)+($F$6="All"))>0)*((('Sales Data'!$D$2:$D$5001=$I$6)+($I$6="All"))>0)*('Sales Data'!$B$2:$B$5001=Z11)*'Sales Data'!$H$2:$H$5001)
B12: PRODUCT | D12: UNIT SOLD BY PRODUCT | K12: TOTAL SALES BY REGION | AA12: =SUMPRODUCT(((('Sales Data'!$C$2:$C$5001=$C$6)+($C$6="All"))>0)*((('Sales Data'!$B$2:$B$5001=$F$6)+($F$6="All"))>0)*((('Sales Data'!$D$2:$D$5001=$I$6)+($I$6="All"))>0)*('Sales Data'!$B$2:$B$5001=Z12)*'Sales Data'!$H$2:$H$5001)
B13: Action Figure
B14: Blender
B15: Moisturizer
B16: Novel
B17: Smartphone
B18: Sneakers
B19: Tent
B22: SALES PERSON
B23: Andrew
B24: Anna
B25: Cameron
B26: Carolyn
B27: Connor | D27: TOTAL SALES BY PRODUCT | K27: TOTAL SALES BY SALES PERSON
B28: Ella
B29: Grace
B30: Megan | D30: TOTAL SALES BY PRODUCT | K30: TOTAL SALES BY SALES PERSON
B31: Nicholas
B32: Virginia
B44: TIP: Add a new row in Sales Data. The dashboard metrics and charts update when Excel recalculates.

Sheet Sales Data
A1: Date | B1: Sales Person | C1: Region | D1: Product | E1: Units Sold | F1: Unit Price | G1: Cost of Goods | H1: Total Sales | I1: Profit | J1: Month | K1: Year
A2: 44246 | B2: Andrew | C2: West | D2: Tent | E2: 84 | F2: 6000 | G2: 4000 | H2: =IF(A2="",0,E2*F2) | I2: =IF(A2="",0,H2-(E2*G2)) | J2: =IF(A2="","",TEXT(A2,"mmm")) | K2: =IF(A2="","",YEAR(A2))
A3: 44446 | B3: Grace | C3: East | D3: Blender | E3: 128 | F3: 3500 | G3: 2500 | H3: =IF(A3="",0,E3*F3) | I3: =IF(A3="",0,H3-(E3*G3)) | J3: =IF(A3="","",TEXT(A3,"mmm")) | K3: =IF(A3="","",YEAR(A3))
A4: 44230 | B4: Ella | C4: South | D4: Action Figure | E4: 136 | F4: 1200 | G4: 800 | H4: =IF(A4="",0,E4*F4) | I4: =IF(A4="",0,H4-(E4*G4)) | J4: =IF(A4="","",TEXT(A4,"mmm")) | K4: =IF(A4="","",YEAR(A4))
A5: 44450 | B5: Cameron | C5: North | D5: Novel | E5: 91 | F5: 1000 | G5: 700 | H5: =IF(A5="",0,E5*F5) | I5: =IF(A5="",0,H5-(E5*G5)) | J5: =IF(A5="","",TEXT(A5,"mmm")) | K5: =IF(A5="","",YEAR(A5))
A6: 44462 | B6: Megan | C6: West | D6: Sneakers | E6: 110 | F6: 4000 | G6: 3000 | H6: =IF(A6="",0,E6*F6) | I6: =IF(A6="",0,H6-(E6*G6)) | J6: =IF(A6="","",TEXT(A6,"mmm")) | K6: =IF(A6="","",YEAR(A6))
A7: 44470 | B7: Carolyn | C7: East | D7: Action Figure | E7: 51 | F7: 1200 | G7: 800 | H7: =IF(A7="",0,E7*F7) | I7: =IF(A7="",0,H7-(E7*G7)) | J7: =IF(A7="","",TEXT(A7,"mmm")) | K7: =IF(A7="","",YEAR(A7))
A8: 44048 | B8: Virginia | C8: North | D8: Novel | E8: 78 | F8: 1000 | G8: 700 | H8: =IF(A8="",0,E8*F8) | I8: =IF(A8="",0,H8-(E8*G8)) | J8: =IF(A8="","",TEXT(A8,"mmm")) | K8: =IF(A8="","",YEAR(A8))
A9: 44141 | B9: Connor | C9: South | D9: Tent | E9: 146 | F9: 6000 | G9: 4000 | H9: =IF(A9="",0,E9*F9) | I9: =IF(A9="",0,H9-(E9*G9)) | J9: =IF(A9="","",TEXT(A9,"mmm")) | K9: =IF(A9="","",YEAR(A9))
A10: 44223 | B10: Anna | C10: West | D10: Moisturizer | E10: 101 | F10: 600 | G10: 400 | H10: =IF(A10="",0,E10*F10) | I10: =IF(A10="",0,H10-(E10*G10)) | J10: =IF(A10="","",TEXT(A10,"mmm")) | K10: =IF(A10="","",YEAR(A10))
A11: 44442 | B11: Nicholas | C11: South | D11: Tent | E11: 52 | F11: 6000 | G11: 4000 | H11: =IF(A11="",0,E11*F11) | I11: =IF(A11="",0,H11-(E11*G11)) | J11: =IF(A11="","",TEXT(A11,"mmm")) | K11: =IF(A11="","",YEAR(A11))
A12: 44104 | B12: Nicholas | C12: East | D12: Action Figure | E12: 55 | F12: 1200 | G12: 800 | H12: =IF(A12="",0,E12*F12) | I12: =IF(A12="",0,H12-(E12*G12)) | J12: =IF(A12="","",TEXT(A12,"mmm")) | K12: =IF(A12="","",YEAR(A12))
A13: 44449 | B13: Nicholas | C13: South | D13: Novel | E13: 137 | F13: 1000 | G13: 700 | H13: =IF(A13="",0,E13*F13) | I13: =IF(A13="",0,H13-(E13*G13)) | J13: =IF(A13="","",TEXT(A13,"mmm")) | K13: =IF(A13="","",YEAR(A13))
... A51: 43958 | B51: Grace | C51: East | D51: Tent | E51: 73 | F51: 6000 | G51: 4000 | H51: =IF(A51="",0,E51*F51) | I51: =IF(A51="",0,H51-(E51*G51)) | J51: =IF(A51="","",TEXT(A51,"mmm")) | K51: =IF(A51="","",YEAR(A51))
H52: =IF(A52="",0,E52*F52) | I52: =IF(A52="",0,H52-(E52*G52)) | J52: =IF(A52="","",TEXT(A52,"mmm")) | K52: =IF(A52="","",YEAR(A52))
H53: =IF(A53="",0,E53*F53) | I53: =IF(A53="",0,H53-(E53*G53)) | J53: =IF(A53="","",TEXT(A53,"mmm")) | K53: =IF(A53="","",YEAR(A53))
H54: =IF(A54="",0,E54*F54) | I54: =IF(A54="",0,H54-(E54*G54)) | J54: =IF(A54="","",TEXT(A54,"mmm")) | K54: =IF(A54="","",YEAR(A54))
H55: =IF(A55="",0,E55*F55) | I55: =IF(A55="",0,H55-(E55*G55)) | J55: =IF(A55="","",TEXT(A55,"mmm")) | K55: =IF(A55="","",YEAR(A55))
H56: =IF(A56="",0,E56*F56) | I56: =IF(A56="",0,H56-(E56*G56)) | J56: =IF(A56="","",TEXT(A56,"mmm")) | K56: =IF(A56="","",YEAR(A56))
H57: =IF(A57="",0,E57*F57) | I57: =IF(A57="",0,H57-(E57*G57)) | J57: =IF(A57="","",TEXT(A57,"mmm")) | K57: =IF(A57="","",YEAR(A57))
H58: =IF(A58="",0,E58*F58) | I58: =IF(A58="",0,H58-(E58*G58)) | J58: =IF(A58="","",TEXT(A58,"mmm")) | K58: =IF(A58="","",YEAR(A58))
H59: =IF(A59="",0,E59*F59) | I59: =IF(A59="",0,H59-(E59*G59)) | J59: =IF(A59="","",TEXT(A59,"mmm")) | K59: =IF(A59="","",YEAR(A59))
H60: =IF(A60="",0,E60*F60) | I60: =IF(A60="",0,H60-(E60*G60)) | J60: =IF(A60="","",TEXT(A60,"mmm")) | K60: =IF(A60="","",YEAR(A60))
H61: =IF(A61="",0,E61*F61) | I61: =IF(A61="",0,H61-(E61*G61)) | J61: =IF(A61="","",TEXT(A61,"mmm")) | K61: =IF(A61="","",YEAR(A61))
H62: =IF(A62="",0,E62*F62) | I62: =IF(A62="",0,H62-(E62*G62)) | J62: =IF(A62="","",TEXT(A62,"mmm")) | K62: =IF(A62="","",YEAR(A62))
H63: =IF(A63="",0,E63*F63) | I63: =IF(A63="",0,H63-(E63*G63)) | J63: =IF(A63="","",TEXT(A63,"mmm")) | K63: =IF(A63="","",YEAR(A63))
... H5001: =IF(A5001="",0,E5001*F5001) | I5001: =IF(A5001="",0,H5001-(E5001*G5001)) | J5001: =IF(A5001="","",TEXT(A5001,"mmm")) | K5001: =IF(A5001="","",YEAR(A5001))

Sheet Lists
A1: All | B1: All | C1: All | D1: Jan
A2: East | B2: Andrew | C2: Action Figure | D2: Feb
A3: North | B3: Anna | C3: Blender | D3: Mar
A4: South | B4: Cameron | C4: Moisturizer | D4: Apr
A5: West | B5: Carolyn | C5: Novel | D5: May
B6: Connor | C6: Smartphone | D6: Jun
B7: Ella | C7: Sneakers | D7: Jul
B8: Grace | C8: Tent | D8: Aug
B9: Megan | D9: Sep
B10: Nicholas | D10: Oct
B11: Virginia | D11: Nov
D12: Dec

Sheet Read Me
A1: SALES DASHBOARD — USER GUIDE
A3: Purpose | B3: Interactive sample sales analysis dashboard with filter-driven KPIs and charts.
A4: 1. Use the Dashboard | B4: Choose Region (C6), Sales Person (F6), and Product (I6) from the dropdowns. Choose All to remove a filter.
A5: 2. Review the KPIs | B5: Total Sales, Average Transaction Sales, Units Sold, and Profit update according to the selected filters.
A6: 3. Update the data | B6: Enter transaction data in Sales Data columns A:G. The calculated columns H:K contain Total Sales, Profit, Month, and Year formulas.
A7: 4. Data capacity | B7: The formulas and SalesTable are prepared for up to 5,000 transaction rows. Keep new transactions within rows 2–5001.
A8: 5. Recalculate | B8: Excel is set to automatic calculation. If results appear stale, press Ctrl+Alt+F9 in Excel to force a full recalculation.
A9: Currency | B9: Values are formatted as Indian Rupees (₹). Confirm the currency before using the workbook with real business data.
A10: Dataset note | B10: The supplied workbook contains 50 sample transactions dated February 5, 2020 through December 21, 2021. These are sample data, not current or actual business results.
A11: Limitations | B11: This is an Excel sample dashboard. Validate formulas and filter behavior in desktop Microsoft Excel after opening; chart rendering can differ in other spreadsheet applications.
